AUTHOR
COPYING
MANIFEST.in
README.rst
setup.py
libcomxml/__init__.py
libcomxml.egg-info/PKG-INFO
libcomxml.egg-info/SOURCES.txt
libcomxml.egg-info/dependency_links.txt
libcomxml.egg-info/requires.txt
libcomxml.egg-info/top_level.txt
libcomxml/core/__init__.py
tests/__init__.py
tests/test_libcomxml.py