Metadata-Version: 1.1
Name: libcomxml
Version: 3.2.0
Summary: This library permits XML generation from Python objects
Home-page: https://github.com/gisce/libComXML
Author: GISCE-TI, S.L
Author-email: devel@gisce.net
License: None
Platform: UNKNOWN
Classifier: Topic :: Text Processing :: Markup :: XML
Classifier: Programming Language :: Python
Classifier: Programming Language :: Python :: 2.7
Classifier: Programming Language :: Python :: 3.5
